{
  "challenge_uid": "22324404-1fef-4d5a-bb03-4774353c66f8",
  "language": "en",
  "dialogues": [
    {
      "dialogue_uid": "f3a511c9-bfb7-4d42-80bf-c22ebfde7957",
      "language": "en",
      "utterances": [
        "That's it.",
        "Dancing fruit in an old TV commercial.",
        "An odd word.",
        "You're not old enough, Lauren.",
        "They heard it through the grapevine - any hint.",
        "That's it.",
        "Okay, California Raisins.",
        "Yeah.",
        "Yeah, you are old enough.",
        "Good.",
        "(Soundbite of laughter)",
        "Part of a typewriter that allows you to go from the end of one line to the start of the next.",
        "Yeah.",
        "Something return.",
        "The…",
        "Yes."
      ]
    },
    {
      "dialogue_uid": "168dddd3-e727-4d90-b565-495f70918055",
      "language": "en",
      "utterances": [
        "Can I help you out?",
        "Yes, you can.",
        "Carriage return.",
        "Carriage return",
        "Carriage return is it.",
        "You know, that's going to go out pretty soon with computers.",
        "That's another one.",
        "No one's going to know from typewriters.",
        "Exactly.",
        "Exactly.",
        "Try this one.",
        "A kind of tube, as in a TV or radio."
      ]
    },
    {
      "dialogue_uid": "8f4d7f97-7f1b-4fd7-9c08-a0725969a982",
      "language": "en",
      "utterances": [
        "Again, we're in the ancient ages.",
        "Gosh.",
        "Any idea?",
        "I've got the radio part but…",
        "It's ray, right?",
        "Cathode ray?",
        "Oh, cathode ray.",
        "Yeah.",
        "Cathode ray.",
        "Cathode ray is it, good.",
        "Mountains in Alberta and British Columbia?",
        "The Cascade Range up there?"
      ]
    },
    {
      "dialogue_uid": "2c1af7ac-2dee-4268-a5d2-f0e38013de47",
      "language": "en",
      "utterances": [
        "No, the Cascade Range - it does go there but they change the name when it gets into Canada.",
        "I'm looking for a more generic term.",
        "Oh, the Canadian Rockies.",
        "Canadian Rockies, is it.",
        "John Steinbeck novel set in Monterey.",
        "Nope, I don't know that one.",
        "Canary Row\"\"?",
        "Canary Row\"\" is it.",
        "Okay.",
        "How about The Beatles label before Apple?",
        "Well, I think, you know this…",
        "You like taking us…",
        "You know, that's the - I don't know.",
        "I don't know."
      ]
    },
    {
      "dialogue_uid": "7e91aff6-68a9-4aa1-8cdf-d60d20890868",
      "language": "en",
      "utterances": [
        "Capital Records.",
        "Capital Records is right.",
        "How about a division of an army on horseback?",
        "Cavalry…",
        "Yes.",
        "Division of an army.",
        "Regiment?",
        "Yeah.",
        "Regiment.",
        "Good.",
        "Good.",
        "Baptism and first communion.",
        "Catholic rites?",
        "That's good.",
        "Non-profit group devoted to finding foster homes for dogs.",
        "And first, you want to think of a word that means relating to dogs.",
        "Canine…"
      ]
    }
  ]
}