{
  "challenge_uid": "185ef721-2ba2-4dba-8f67-899ccdea4991",
  "language": "en",
  "dialogues": [
    {
      "dialogue_uid": "16fa6451-266c-49c3-97e9-ea921cb39a5f",
      "language": "en",
      "utterances": [
        "You were, in a sense, though, cocooned until you got to New York by the fact that you so often worked with your father.",
        "Yeah, and I had the huge advantage of not only a backlog of experience onstage, but I knew what the business was to a great extent.",
        "I knew how hard it was.",
        "I knew what I was in for.",
        "But even so, I suffered a couple of brutal years of unemployment and could not get any traction even with all my - with my huge head start and with my Harvard training, London Academy training and a year, a convenient father directing a repertory company who was all ready to hire me to get me going.",
        "In fact, you, at one point established your own repertory company.",
        "Yes, you'll notice I have not established one since.",
        "(SOUNDBITE OF LAUGHTER)",
        "The Great Road Players.",
        "That's right.",
        "That was my own total catastrophe.",
        "Well, so far.",
        "So far.",
        "(SOUNDBITE OF LAUGHTER)"
      ]
    },
    {
      "dialogue_uid": "e0382c76-080d-46b8-9909-8c9af599b599",
      "language": "en",
      "utterances": [
        "You're young yet.",
        "John Lithgow is with us.",
        "His book again is titled \"\"Drama: An Actor's Education.\"\" If you are a parent and work in the arts, do you want your children to follow that often difficult path?",
        "Give us a call, 800-989-8255.",
        "Email us, talk@npr.org.",
        "Stay with us.",
        "I'm Neal Conan.",
        "It's the TALK OF THE NATION from NPR News.",
        "(SOUNDBITE OF MUSIC)",
        "This is TALK OF THE NATION from NPR News.",
        "I'm Neal Conan.",
        "John Lithgow is our guest, well-known of course for his role in comedies, TV and film.",
        "His most recent Emmy, however, came for his chilling performance as the Trinity killer on the Showtime series \"\"Dexter.",
        "(SOUNDBITE OF TELEVISION PROGRAM, \"\"DEXTER\"\")",
        "(SOUNDBITE OF MUSIC)",
        "(As Arthur Mitchell) You just need to let go and fall.",
        "(As character) Please, I'll do anything.",
        "(As Mitchell) Good, jump.",
        "(As character) No, I can't.",
        "(As Mitchell) You can."
      ]
    },
    {
      "dialogue_uid": "50e3a7f9-0acc-407a-ae72-1454e561118c",
      "language": "en",
      "utterances": [
        "(As Mitchell) I have children.",
        "(As Mitchell) I know, Jason and Suzie.",
        "If you'd like, I could swing by your house, put a ice pick in your husband's head and bring your kids back and throw them off one at a time until you finally decide to jump.",
        "Is that what you want?",
        "Actually, I wanted to change the channel and watch \"\"Harry and the Hendersons.",
        "(SOUNDBITE OF LAUGHTER)",
        "Well, that was the real me.",
        "John Lithgow's memoir was released earlier this year and is one of our Books We Missed.",
        "In it, he writes that one of his earliest roles, while just a toddler, put him onstage playing the role of son to his actual father Arthur Lithgow.",
        "Eventually, he grew into the family business, so to speak.",
        "So if you are a parent and work in the arts field fraught with rejection, how do you want your children to grow up and follow your path?",
        "Give us a call, 800-989-8255.",
        "Email talk@npr.org.",
        "You can also join the conversation on our website.",
        "Go to npr.org.",
        "Click on TALK OF THE NATION.",
        "Let's go next to Jim, and Jim's on the line from Grand Rapids.",
        "Hi, it's Tim.",
        "Hi, Jim, it's John."
      ]
    },
    {
      "dialogue_uid": "d37c7f6f-5252-4e02-a17d-474e809a782d",
      "language": "en",
      "utterances": [
        "Hi, John.",
        "I love all the work that you have done throughout the years.",
        "Thank you.",
        "You have done what Viola Spolin, you're probably familiar with her.",
        "She always said share with your audience.",
        "And it seems like you're the kind of actor that does that.",
        "Well, they give a lot to me.",
        "They share a lot with me.",
        "Do you have a child going into the business, Jim?",
        "No, I make my living though as an entertainer, and I started out in children's theater.",
        "And one thing led to another and do TV commercials and radio commercials and ended up working in radio.",
        "And my kids, now 13 and 15, you know, when their parents, you know, find out maybe who I am what I do, but when their friends say so what does your dad do?",
        "And they just kind of throw it off these days, well, he just does shows.",
        "You know, they have no idea.",
        "Their friends are like he does what?",
        "And they don't come to the comedy clubs, or they don't, you know, see most of what I do.",
        "But there's part of me that's torn that I kind of would like to see my kids sometimes onstage, when they've done little things here or there, that I want them to go for it.",
        "At the same time, it's one of those lives that you live that if the phone doesn't ring, you don't work.",
        "Yeah, yeah.",
        "And it's really - you're torn with it because you're - and for me I guess if they really love it, if they get bit by the bug, then I guess you're going to pursue it, and you're going to do some version of it.",
        "If not, that's OK, too.",
        "All right, Jim, well, thanks very much for the call.",
        "John Lithgow, of course far too grand an actor to stoop to commercials."
      ]
    },
    {
      "dialogue_uid": "89e0bad3-20ee-4c1c-9002-5e2a26b2e879",
      "language": "en",
      "utterances": [
        "Oh no, no, I've done my commercials.",
        "I've done a few commercials, but I've probably only done about 2 percent of the commercials that I've auditioned for, so...",
        "(SOUNDBITE OF LAUGHTER)",
        "There's a very funny chapter in the book of your auditioning for commercial after commercial.",
        "He says if they left, I would go crazy.",
        "That's right.",
        "Before I ever got one, you know, after I'd done 100 unsuccessful auditions, I said oh, well, at least now I can tell everybody I don't do commercials because they're beneath me.",
        "(SOUNDBITE OF LAUGHTER)",
        "That all ended when I finally did a few.",
        "Let's get Elaine on the line, Elaine with us from Rochester in New York.",
        "Hi, my husband and I met when he was doing regional theater and children's theater.",
        "When our daughter was born, he cut way back because he wanted to be home to see her at night.",
        "Yeah, yeah."
      ]
    }
  ]
}