{
  "challenge_uid": "a45bcf3c-8116-4aa5-a994-086bb06f79ed",
  "language": "en",
  "dialogues": [
    {
      "dialogue_uid": "430df1a5-767b-41ce-9198-ff4ce4c0f576",
      "language": "en",
      "utterances": [
        "Unidentified Man #1: All the way, there was…",
        "Unidentified Man #3: The curds and the American way, from the old nursery rhyme.",
        "Unidentified Man #1: Yeah.",
        "Unidentified Man #2: Yes.",
        "Unidentified Man #1: Little Miss Muffett.",
        "Yes.",
        "Unidentified Man #1: And her American curds and whey.",
        "And her American curds and whey.",
        "There you have it, Craig.",
        "Bye, bye.",
        "Let's go now to David, and David's calling us from, what is this, Lenore, is that right, in North Carolina?",
        "Lenore."
      ]
    },
    {
      "dialogue_uid": "117f4cc4-6093-4e8e-a6d9-b29cf3bb36ad",
      "language": "en",
      "utterances": [
        "Lenore, as in the Edgar Allen Poe poem.",
        "Go ahead.",
        "Yeah.",
        "George Washington, um, didn't he have, like, many affairs?",
        "Wasn't he like known for a man who had many women, slave women and, I want to get you all's take on that.",
        "Unidentified Man #1: No. American presidents only sleep with their wives.",
        "Unidentified Man #2: Yes.",
        "Unidentified Man #1: I think that's, I think that's, yeah…",
        "Unidentified Man #2: That's been true through every, with every single American president.",
        "Was Thomas Jefferson married to what's her name?",
        "Anyway, go ahead.",
        "Unidentified Man #3: (Unintelligible) the whole…",
        "Unidentified Man #2: Moving right along.",
        "Unidentified Man #3: It's a whole thing.",
        "No, I think it's a proud American tradition, American presidential tradition, of sleeping with your slaves."
      ]
    },
    {
      "dialogue_uid": "35fcd3bd-a646-4439-9128-a29b00644d11",
      "language": "en",
      "utterances": [
        "Unidentified Man #1: Well, we travel around the country, and it looks like George Washington slept everywhere.",
        "So it's probably true.",
        "Yeah.",
        "Unidentified Man #3: It's probably true.",
        "Unidentified Man #2: Seriously, the word on Washington is he was caught falling out of some bedroom windows as old as like 65 or so, so he was a player.",
        "Unidentified Man #1: Wow.",
        "Unidentified Man #3: He was a player.",
        "Unidentified Man #1: A play-ah.",
        "Unidentified Man #3: Washington was getting - Washington got busy.",
        "(Soundbite of laughter)",
        "Unidentified Man #2: Apparently this wasn't just a president who got busy, he got biz-aay.",
        "Unidentified Man #3: Biz-aay.",
        "I think he got biz-aay with Betsy Ross, too, because that's a whole mythology surrounding here."
      ]
    },
    {
      "dialogue_uid": "cf8a77aa-6012-49ba-a132-b0111dea5a46",
      "language": "en",
      "utterances": [
        "Unidentified Man #1: So apparently it's true.",
        "He was the father of most of our country.",
        "Unidentified Man #2: And then she could sew him some pants.",
        "Unidentified Man #3: Yeah!",
        "Betsy Ross went down in history in a completely way then we think.",
        "Unidentified Man #2: Some monogrammed underwear, maybe.",
        "So that, thank you very much for the call, David, but that leads me to ask the question, when you, get on people like, G-Dub(ph), for example, how do you decide - history's a very sensitive topic, I mean, being seriously, people will take offense at various things.",
        "Who do you decide - you're almost deciding who to offend and who not to.",
        "Unidentified Man #1: We try to be equal opportunity offenders.",
        "We, you know, whoever's the current president, we blasted Clinton when he was in office.",
        "And now W gets a few shots, and, you know.",
        "Unidentified Man #3: Yeah.",
        "People say you shouldn't be making fun of the president, and we say look, we'd much rather be making fun of Kerry, but that's not the way it worked out.",
        "Unidentified Man #2: Yeah.",
        "If Kerry won we'd be swinging away.",
        "Unidentified Man #3: We'd be swinging away at him too.",
        "I mean, it's guaranteed that somebody's going to be offended by something.",
        "And so, we just try to really make it funny.",
        "Unidentified Man #1: We do an Abraham Lincoln assassination ballet.",
        "And occasionally, we get people come up to us that says you just can't joke about that."
      ]
    },
    {
      "dialogue_uid": "f9179f61-c861-4bab-a2c7-3c7152389b81",
      "language": "en",
      "utterances": [
        "Unidentified Man #2: It's too soon.",
        "Unidentified Man #1: It's too soon.",
        "And, okay, but what is the statute of limitations on that?",
        "I don't know.",
        "Unidentified Man #1: We're still finding it.",
        "Unidentified Man #3: Tragedy plus time equals comedy.",
        "Maybe next time you can actually play Ford's Theatre and see how it goes over there.",
        "Unidentified Man #2: I would love to.",
        "How eerie would that be?",
        "Let's get another caller on.",
        "This is Charles.",
        "Charles calling from Mankato in Minnesota.",
        "Well good afternoon, good morning, depending on where you are.",
        "Unidentified Man #1: Happy Fourth of July to all of us.",
        "Happy Fourth of July.",
        "Nice Anglo-American holiday that we're celebrating."
      ]
    }
  ]
}