{
  "challenge_uid": "d350bdb6-2a57-4721-8285-34ef8bedca21",
  "language": "en",
  "dialogues": [
    {
      "dialogue_uid": "b652ceb3-4497-4772-885a-a4b9a09ec996",
      "language": "en",
      "utterances": [
        "Say, wow...",
        "Well, here's the...",
        "...That was great.",
        "But here's the hard question.",
        "Is this part of it - is it the celebrity deaths in part, or is it the election...",
        "I think...",
        "...Which was so ugly.",
        "I mean...",
        "Yeah.",
        "I - to me...",
        "Is it partly that?",
        "You know, to me, it was just - the election - the whole energy of it was so negative - people tearing each other down, calling each other names.",
        "You know, just - gosh, it was really negative and nasty compared with - in 2008, there was more of a sense of, this actually is a bad year; we need to pull together and do the best we can.",
        "Interesting.",
        "Nate, what do you think?"
      ]
    },
    {
      "dialogue_uid": "4acd453c-5096-4e1d-b6e9-5053fad60919",
      "language": "en",
      "utterances": [
        "You know, no, it wasn't the years - worst year ever.",
        "I mean we could all hope that it's the worst year ever because that means 2017, like - things are looking up, right?",
        "I tried taking a positive tact on this because I do think that, you know, you are what you eat, right?",
        "So, like, I think if we look at all this negative news, you consume all this negative news, I mean, yeah, the world looks pretty bleak and terrible.",
        "So I was trying to pick my brain earlier and think of things that were really good this year.",
        "And I think objectively, we can say it was a great year for sports.",
        "The Cubs won the World Series.",
        "They broke their curse.",
        "That was pretty exciting.",
        "LeBron James fulfilled his prophecy and brought a championship...",
        "Yay.",
        "Oh, OK.",
        "...to Cleveland.",
        "You don't sound so excited, Sam.",
        "I don't.",
        "(LAUGHTER)",
        "I loved it, said...",
        "Sam, it's OK."
      ]
    },
    {
      "dialogue_uid": "9c31d29c-ad6a-4784-a30e-0687c79719cc",
      "language": "en",
      "utterances": [
        "...The Buckeye.",
        "(Laughter).",
        "That's all right.",
        "I am a unhealthy Denver Broncos fan, and we won the Super Bowl, so that's really good.",
        "So I mean I think there were - everything's relative, right?",
        "I think for some people, it was, yeah, a really, really, really bad year.",
        "For some people, it wasn't so bad.",
        "And it's important to remember that.",
        "And for Trump supporters, it was a great year.",
        "It was a great year.",
        "I mean one of our guests - one of our earlier Barbershop guests earlier in the year was saying, look; now we get a chance to see our ideas in practice.",
        "But moving on from that, let's just - all right, you know, we were looking at a lot of the lists that were together by lots of news organizations about, like, the biggest stories of 2016.",
        "And it was interesting, Nate, going back to your point, about kind of where you stand depends on where you sit...",
        "Right.",
        "...Or what you focus on yourself.",
        "So let me just start with you on that.",
        "What's your take on the biggest and most important story in 2016?",
        "Well, I mean it's hard to argue that the election wasn't the biggest story of 2016.",
        "I was trying to think of some stories that we're going to think about in, like, 10 years, right?",
        "We're going to look back and say, oh, 2016 - that happened."
      ]
    },
    {
      "dialogue_uid": "e3b4d7c3-c321-4ed6-a3bb-95f4f3385731",
      "language": "en",
      "utterances": [
        "OK.",
        "Let's meet the contestants for Miss Shrimp Festival 2011 - right now.",
        "Hi.",
        "My name is Bethany...",
        "And I think a story that didn't get a ton of play, was kind of overwrought with all the other stuff during the election - but cannabis, marijuana - now 1 in 5 Americans live in a state where recreational pot is legal for adults.",
        "And people that I've talked to in the cannabis industry say it's a game changer.",
        "It's a turning point, a tipping point, whatever you want to call it there.",
        "And I do think that that is something that we are going to be talking about going forward.",
        "One other thing that I know is not sexy - I'm stepping out on a limb here.",
        "But public lands, land-use issues are near and dear to my heart, and they're a big thing out here in the West.",
        "And they don't usually get that much attention because they just really aren't that interesting.",
        "It's kind of boring and complicated.",
        "And people on the East Coast don't really understand it as much just because public lands aren't as big of an issue there, but they've been in the news a ton this year, and those are big things I think we need to talk about if you're looking at this urban-rural divide and what what's important to people in different parts of the country.",
        "Interesting idea.",
        "Marilyn, you want to jump in on this?",
        "What's your idea of the...",
        "Yeah.",
        "What do you think is the biggest story of 2016?",
        "You know, what was a big story seemed...",
        "And it could be something you covered.",
        "I mean don't be modest."
      ]
    },
    {
      "dialogue_uid": "2775dfe6-ac95-47a6-8263-86446ece7530",
      "language": "en",
      "utterances": [
        "Well, it seemed small in a way, and yet it was a huge story.",
        "The Carrier plant where the people got laid off - it's a good example of why things - negative news gets amplified.",
        "And I named all those things that were great about the economy.",
        "Stocks are up and this and that.",
        "There are all these good things that happened.",
        "But when you watch that video that somebody made with the little handheld smartphone, you get this video of people being told their lives are being shattered.",
        "You're going to lose your job, and the way that guy did it was so cold.",
        "It was like, and we're going to move, and you're going to lose your job and blah, blah, blah.",
        "And these people - you could just hear this gasp of people saying, oh, my God.",
        "You know, your life is about to fall apart, and this guy's just rattling on.",
        "So that ability to take something that was a relatively small story but amplified across social media made people feel like 2016 was a lot worse than it was.",
        "I think that Carrier story really had an impact on the election and an impact on how we thought about trade deals, how it helped kill off the Trans-Pacific Partnership deal.",
        "Those - that story reverberated in interesting ways.",
        "Sam, what about you?",
        "Yeah, I mean I think the default for someone who covers politics like me would be to say the story of the year was the election or Donald Trump or Russia.",
        "But I want to peel back those top layers and argue that the real story of this year was America's changing consumption of news and media...",
        "Yeah.",
        "...And how that is shaping everything that's going on right now.",
        "It definitely shaped this election.",
        "I mean think about it.",
        "We have seen this new economy where people are consuming the news not from an NPR website or a Washington Post website but from their social media feeds.",
        "They are feed first, social media first.",
        "We've seen the rise of fake news.",
        "We've seen the rise of fake interaction in spaces like Twitter with all these bots doing God knows what.",
        "And so we've seen people more plugged in and more free to access all this information.",
        "But all of this freedom seems to have made us more divided.",
        "And my question going forward for the next year is, like, what do we as journalists do to fix that problem?",
        "We have to ask ourselves every day, are we helping (laughter) 'cause, like, that needs to be fixed, and I'm not sure how.",
        "And that is not a bad question to ask."
      ]
    }
  ]
}