{
  "challenge_uid": "9e95bcf9-1aad-4c0c-b8a4-44ebabf1122d",
  "language": "en",
  "dialogues": [
    {
      "dialogue_uid": "0d04d96c-f7c7-4390-b121-019ce4bb3f14",
      "language": "en",
      "utterances": [
        "Chris Christie says it's dangerous, rising libertarianism.",
        "I agree with that, but it's there.",
        "I don't view it that way.",
        "I actually thought this was kind of a wonderful thing.",
        "Justin Amash, 33-year-old libertarian, John Conyers, 84-year-old liberal, say wait a minute, we have some questions to ask about the NSA.",
        "And the vote was as bipartisan as you'll ever find, 94 Republicans and 111 Democrats for it.",
        "I don't think this is a vote to make us less secure.",
        "I think people have a lot of legitimate questions about the national security state.",
        "Great piece in David's paper about this FISA court, all the appointees being Republican.",
        "Let's open this debate.",
        "This was a vote to keep it open.",
        "Well, I think we do have the debate, but we do have a situation where according to most of the people who actually know what they're talking about, these programs have saved lives.",
        "David Brooks and E.J.",
        "Dionne, thanks to both of you.",
        "Thank you.",
        "Thank you.",
        "OK.",
        "If you're under 25 and you're listening, for those of us who aren't, we're about to discuss some vocabulary The Boston Globe language columnist Ben Zimmer says you already know.",
        "Ben Zimmer, let's do this thing.",
        "Yolo.",
        "Yolo."
      ]
    },
    {
      "dialogue_uid": "5bce4ac7-519a-4f98-b5a2-ab819944c905",
      "language": "en",
      "utterances": [
        "Yolo.",
        "It's an acronym that stands for you only live once, and Ben Zimmer says it's the buzzword of the year for teenagers and young adults.",
        "Especially after a song, \"\"The Motto,\"\" by the rapper Drake came out.",
        "(SOUNDBITE OF SONG, \"\"THE MOTTO\"\")",
        "(Rapping) Now she want a photo.",
        "You already know though.",
        "You only live once; that's a motto.",
        "Yolo.",
        "We 'bout it every day, every day, every day.",
        "When the video came out in February, all of a sudden, yolo was everywhere.",
        "And that's where it started?",
        "Well, you can find precursors, definitely.",
        "The full expression \"\"you only live once\"\" goes back a long ways.",
        "That's not new, right?",
        "Yeah.",
        "Not at all.",
        "No. But this year is really the year of yolo, thanks to that song \"\"The Motto,\"\" and how it then spread.",
        "(SOUNDBITE OF SONG, \"\"THE MOTTO\"\")"
      ]
    },
    {
      "dialogue_uid": "2deeb153-3369-4f6d-be4c-c8f20ccd65b4",
      "language": "en",
      "utterances": [
        "(Rapping) Now she want a photo.",
        "You already know though.",
        "You only live once.",
        "That's a motto.",
        "Yolo.",
        "We bout it every day...",
        "It's a fascinating shibboleth, an expression that really marks one group from another.",
        "If you're young, you know yolo.",
        "In fact, yolo seems to encapsulate something about youthful behavior, sort of crazy, reckless behavior and living that way without worrying too much about the consequences.",
        "So how would you use it, for example?",
        "You could say, you know, I got so wasted last night.",
        "Yolo.",
        "That would be a sort of a retrospective yolo talking about something that happened in the past.",
        "More - a more thoughtful yolo.",
        "A more thoughtful yolo.",
        "Well, you know, you could be weighing different decisions.",
        "You want to park illegally in this spot?",
        "Yolo.",
        "Should I buy these shoes or pay rent?",
        "Yolo.",
        "So it can just get tacked on that way.",
        "It can also be used as a verb.",
        "You can talk about yolo-ing as a way to talk about expressing that youthful vitality, let's say.",
        "Hmm.",
        "Ben, yolo, I would suspect, is going to have a short shelf life because I understand that Katie Couric, when she launches her new talk show, is going to have a segment called \"\"What's Your Yolo?\"\" which is quite possibly the fastest way to make that term uncool.",
        "(LAUGHTER)",
        "What Katie Couric is doing with this segment is encouraging viewers to write in or make videos that they submit to the show talking about what's the thing that you want to do before you die.",
        "What do you want to cross off your bucket list?",
        "So she's turned yolo into bucket list."
      ]
    },
    {
      "dialogue_uid": "330251f9-c099-4132-813a-91f98ec8bada",
      "language": "en",
      "utterances": [
        "(LAUGHTER)",
        "Right.",
        "So that yolo expression, the way she's using it, is turning it to something else and certainly nothing related to that kind of youth culture that it came out of.",
        "So if Katie Couric is latching on to it, that may really signal the death knell of yolo.",
        "See, I was always under the impression of yolt.",
        "You only live twice.",
        "You only live twice, right?",
        "(SOUNDBITE OF SONG, \"\"YOU ONLY LIVE TWICE\"\")",
        "(Singing) You only live twice...",
        "Right.",
        "So that was the James Bond novel which turned into the movie with the Nancy Sinatra theme song.",
        "It was recently used on the show \"\"Mad Men.\"\" When that song was on the show in June, there were people who were making that connection between yolo, you only live once, and yolt, you only live twice.",
        "(SOUNDBITE OF SONG, \"\"YOU ONLY LIVE TWICE\"\")",
        "(Singing) You only live twice..."
      ]
    },
    {
      "dialogue_uid": "1be0503b-6748-4d9a-9fbf-32d6c4aab6fe",
      "language": "en",
      "utterances": [
        "(SOUNDBITE OF SONG, \"\"THE MOTTO\"\")",
        "(Rapping) What's up?",
        "What's up?",
        "What's up?",
        "What's up, what's up...",
        "That's Ben Zimmer, language columnist for the Boston Globe.",
        "He recently wrote about the term yolo.",
        "Ben, yolo.",
        "Yolo.",
        "(SOUNDBITE OF SONG, \"\"THE MOTTO\"\")",
        "(Rapping) Now she want a photo.",
        "You already know though.",
        "You only live once.",
        "That's a motto.",
        "You're listening to ALL THINGS CONSIDERED from NPR News.",
        "It's MORNING EDITION from NPR News.",
        "Good morning, I'm Renee Montagne.",
        "But not all the groups favored by the bill are closely aligned with Democrats.",
        "As Utah Republican Bob Bennett pointed out, House Democrats earlier altered the DISCLOSE Act to carve out some strategic exemptions.",
        "As about 10 of us gathered around the churn, which basically looks like a gallon sized glass jar with a crank on top, there's a sense that the show is about to begin.",
        "And as two kids beat on a toy drum, the mood is part ceremony, part circus."
      ]
    }
  ]
}