{
  "challenge_uid": "581bfcf0-dbfa-4fc4-b237-1f62e017e84b",
  "language": "en",
  "dialogues": [
    {
      "dialogue_uid": "f03d2ca9-3605-404e-864d-4f5299364f02",
      "language": "en",
      "utterances": [
        "Since Mr. Shortz was at Games magazine.",
        "So like...",
        "Woah.",
        "Well over 20 years I think.",
        "Nice.",
        "So that must make the victory especially sweet.",
        "Yeah, especially when I hear people that have been on more than once or, you know, win with their first entry, so.",
        "And Craig, what you do for a living?",
        "I am a news photographer at a TV station in Detroit.",
        "Excellent.",
        "That sounds like an exciting job.",
        "It can be.",
        "It can be.",
        "So Craig, are you ready to play the puzzle?"
      ]
    },
    {
      "dialogue_uid": "5fa2355a-0dcd-4994-94b5-8034a41c0327",
      "language": "en",
      "utterances": [
        "I am ready.",
        "OK, let's play.",
        "All right, Craig and Arun.",
        "Today's puzzle is called ch-ch-ch-changes.",
        "Every answer is a word starting with the letters C-H, which I'd like you to get from its anagram.",
        "For example, if I said C-H plus tale - T-A-L-E, you should say chale.",
        "So it always starts with C-H.",
        "Your first one is C-H plus cane, C-A-N-E.",
        "C-H-C-A-N-E.",
        "Think I got this.",
        "Oh, OK go ahead, Arun.",
        "Is it chance?",
        "Chance is it, good.",
        "All right.",
        "Number two is C-H plus lies, L-I-E-S.",
        "Think of a tool.",
        "A chisel.",
        "Chisel is it.",
        "C-H plus sour, S-O-U-R."
      ]
    },
    {
      "dialogue_uid": "7f8e1510-bf7c-4c2f-8e56-5e33dc308bd8",
      "language": "en",
      "utterances": [
        "Chorus.",
        "Good one.",
        "Chorus is it.",
        "C-H plus nose, N-O-S-E.",
        "Chosen.",
        "Excellent.",
        "C-H plus more, M-O-R-E.",
        "Arun?",
        "I'm... (Laughing).",
        "That ball's thrown into your court.",
        "This is a little tricky 'cause it does not - the next letter is not a vowel.",
        "It's one of the consonants.",
        "Chrome.",
        "Chrome is it.",
        "C-H plus plea, P-L-E-A."
      ]
    },
    {
      "dialogue_uid": "0adb6f17-cc14-463a-9f92-20d3110b1dd8",
      "language": "en",
      "utterances": [
        "Chapel.",
        "Yeah.",
        "Plus rube, R-U-B-E.",
        "Cherub.",
        "Plus eyes, E-Y-E-S.",
        "Cheesy.",
        "Cheesy is it.",
        "I'm not cheesy.",
        "Oh, that's your answer.",
        "Sorry.",
        "No, no.",
        "Plus grain, G-R-A-I-N."
      ]
    },
    {
      "dialogue_uid": "52680e20-03ae-4df3-b8ab-a073db5c57b7",
      "language": "en",
      "utterances": [
        "Is that chagrin?",
        "Excellent.",
        "Nice.",
        "Plus times, T-I-M-E-S.",
        "Chemist?",
        "Mary Jane Smith ran some of Ron Paul's early campaigns, at first operating out of the den of the family's ranch-style home.",
        "Members of the Methodist church choir and the PTA were drafted to help sort incoming mail, and libertarian economists were frequent guests at family dinners.",
        "They were always around the kitchen table.",
        "The kids would come and have dinner, and I remember Randy sitting there, being there.",
        "And I've heard him say as an adult, I just learned so much by just listening.",
        "Rand Paul listened carefully and absorbed much of his father's small government philosophy.",
        "Before he tried taking a scalpel to government, though, Rand Paul followed his father into medicine.",
        "Pyeatt shows me a high school yearbook with a striking photo of young Randy in anatomy class, smiling as he dissects a cat.",
        "He said - when he was a very young man, he said, I'm going to be a medical doctor.",
        "He knew exactly what he wanted to be and exactly what he needed to do to get there and be successful.",
        "In 1981, Paul went off to college at Baylor University in Waco, taking his homegrown politics along.",
        "He joined a new political organization, the Young Conservatives of Texas.",
        "Founder Steve Munisteri says Paul quickly distinguished himself, offering a college-aged preview of his speaking ability that would later make him a C-SPAN sensation."
      ]
    }
  ]
}